pyglom
