Metadata-Version: 2.1
Name: pyglom
Version: 0.0.3
Summary: PyTorch implementation of GLOM. PyTorch-Lightning version is also available.
Home-page: https://github.com/YeonwooSung/GLOM
Author: Yeonwoo Sung
Author-email: neos960518@gmail.com
License: MIT
Keywords: AI,artificial intelligence,deep learning,glom,neuralnet,neural network,NN
Platform: UNKNOWN
Classifier: Development Status :: 4 - Beta
Classifier: Intended Audience :: Developers
Classifier: Topic :: Scientific/Engineering :: Artificial Intelligence
Classifier: License :: OSI Approved :: MIT License
Classifier: Programming Language :: Python :: 3.6
